topsis/__init__.py
topsis/__main__.py
Topsis_Lovish_101917087-1.0.0.dist-info/LICENSE
Topsis_Lovish_101917087-1.0.0.dist-info/METADATA
Topsis_Lovish_101917087-1.0.0.dist-info/WHEEL
Topsis_Lovish_101917087-1.0.0.dist-info/entry_points.txt
Topsis_Lovish_101917087-1.0.0.dist-info/top_level.txt
Topsis_Lovish_101917087-1.0.0.dist-info/RECORD
